{
  "metadata": {
    "school_id": "LEMM803035",
    "denominazione": "Falcone E Borsellino - Patu'",
    "tipo_scuola": "I Grado",
    "ordine_grado": "I Grado",
    "area_geografica": "Sud",
    "territorio": "Non Metropolitano",
    "comune": "Patu'",
    "anno_ptof": "2019/2022",
    "provincia": "Lecce",
    "regione": "Puglia",
    "statale_paritaria": "Statale",
    "indirizzo": "Via G. Romano 16",
    "cap": "73053",
    "email": "leic803002@istruzione.it",
    "pec": "ND",
    "website": "www.comprensivosalvemorciano.gov.it"
  },
  "ptof_section2": {
    "2_1_ptof_orientamento_sezione_dedicata": {
      "has_sezione_dedicata": 0,
      "score": 2,
      "note": "L'orientamento non è trattato in una sezione dedicata. Viene menzionato implicitamente nella 'Presentazione della Scuola' e nei 'Progetti proposti' ma in modo frammentario."
    },
    "2_2_partnership": {
      "partner_nominati": [
        "Consultorio Familiare",
        "ASL",
        "Cittadinanza Attiva",
        "auditorium della Conciliazione",
        "teatro Ghione",
        "biblioteca comunale Valle Aurelia",
        "enti culturali",
        "famiglie",
        "funzionario educativo (G.L.H.)",
        "operatori della A.S.L."
      ],
      "partnership_count": 10
    },
    "2_3_finalita": {
      "finalita_attitudini": {
        "score": 3,
        "evidence_quote": "promuovere lo sviluppo dell’identità, dell’autonomia, della competenza",
        "evidence_location": "Pagina 3"
      },
      "finalita_interessi": {
        "score": 3,
        "evidence_quote": "stimolare il bambino a conoscere e sentire le proprie esigenze",
        "evidence_location": "Pagina 3"
      },
      "finalita_progetto_vita": {
        "score": 2,
        "evidence_quote": "nessuna esplicita menzione",
        "evidence_location": "N/A"
      },
      "finalita_transizioni_formative": {
        "score": 3,
        "evidence_quote": "Continuità Nido-Scuola dell’Infanzia",
        "evidence_location": "Pagina 19"
      },
      "finalita_capacita_orientative_opportunita": {
        "score": 2,
        "evidence_quote": "nessuna esplicita menzione",
        "evidence_location": "N/A"
      }
    },
    "2_4_obiettivi": {
      "obiettivo_ridurre_abbandono": {
        "score": 1
      },
      "obiettivo_continuita_territorio": {
        "score": 4
      },
      "obiettivo_contrastare_neet": {
        "score": 1
      },
      "obiettivo_lifelong_learning": {
        "score": 2
      }
    },
    "2_5_azioni_sistema": {
      "azione_coordinamento_servizi": {
        "score": 4
      },
      "azione_dialogo_docenti_studenti": {
        "score": 2
      },
      "azione_rapporto_scuola_genitori": {
        "score": 5
      },
      "azione_monitoraggio_azioni": {
        "score": 2
      },
      "azione_sistema_integrato_inclusione_fragilita": {
        "score": 5
      }
    },
    "2_6_didattica_orientativa": {
      "didattica_da_esperienza_studenti": {
        "score": 5
      },
      "didattica_laboratoriale": {
        "score": 6
      },
      "didattica_flessibilita_spazi_tempi": {
        "score": 3
      },
      "didattica_interdisciplinare": {
        "score": 4
      }
    },
    "2_7_opzionali_facoltative": {
      "opzionali_culturali": {
        "score": 1
      },
      "opzionali_laboratoriali_espressive": {
        "score": 5
      },
      "opzionali_ludiche_ricreative": {
        "score": 4
      },
      "opzionali_volontariato": {
        "score": 1
      },
      "opzionali_sportive": {
        "score": 3
      }
    }
  },
  "activities_register": [
    {
      "titolo_attivita": "Progetti con il territorio",
      "categoria_principale": "Progetto",
      "descrizione_e_metodologia": "Visite a luoghi di interesse storico-artistico e culturale del territorio.",
      "5w_chi": "Tutti i bambini",
      "5w_cosa": "Visite guidate a musei, chiese, parchi.",
      "5w_dove": "Città del Vaticano, Castel Sant’Angelo, parchi comunali.",
      "5w_quando": "Durante l'anno scolastico",
      "5w_perche": "Conoscere il territorio e il patrimonio culturale.",
      "ore_dichiarate": "ND",
      "target": "Tutti",
      "evidence_quote": "La Scuola dell’Infanzia Comunale si trova nel suggestivo quartiere di Santa Maria delle Fornaci a pochi passi da San Pietro.",
      "evidence_location": "Pagina 4"
    },
    {
      "titolo_attivita": "Orto-giardino",
      "categoria_principale": "Laboratorio",
      "descrizione_e_metodologia": "Attività manuale all’aperto per coltivare piante aromatiche e fiori, stimolando i sensi e l'esplorazione.",
      "5w_chi": "Bambini",
      "5w_cosa": "Realizzazione e cura di un orto.",
      "5w_dove": "Scuola",
      "5w_quando": "Non specificato",
      "5w_perche": "Sviluppare abilità scientifiche, curiosità e rispetto per l'ambiente.",
      "ore_dichiarate": "ND",
      "target": "Tutti i bambini",
      "evidence_quote": "stimolati ad utilizzare i propri sensi per mettersi in “contatto con la natura”",
      "evidence_location": "Pagina 16"
    },
    {
      "titolo_attivita": "Laboratorio sensoriale",
      "categoria_principale": "Laboratorio",
      "descrizione_e_metodologia": "Esplorazione dei 5 sensi attraverso la manipolazione di materiali e attività ludiche.",
      "5w_chi": "Bambini",
      "5w_cosa": "Scoperta dei 5 sensi e sviluppo di capacità percettive ed espressive.",
      "5w_dove": "Scuola",
      "5w_quando": "Non specificato",
      "5w_perche": "Sviluppare il sistema sensoriale, la creatività e l'espressione emotiva.",
      "ore_dichiarate": "ND",
      "target": "Tutti i bambini",
      "evidence_quote": "accompagnare i bambini alla scoperta dei 5 sensi",
      "evidence_location": "Pagina 17"
    },
    {
      "titolo_attivita": "Psicomotricità",
      "categoria_principale": "Laboratorio",
      "descrizione_e_metodologia": "Attività motorie per sviluppare il controllo del corpo, la coordinazione e la socializzazione.",
      "5w_chi": "Bambini di 3 anni",
      "5w_cosa": "Esercizi motori e giochi di gruppo.",
      "5w_dove": "Scuola",
      "5w_quando": "Non specificato",
      "5w_perche": "Sviluppare la motricità, l'autostima e lo spirito di gruppo.",
      "ore_dichiarate": "ND",
      "target": "Bambini di 3 anni",
      "evidence_quote": "risposta al bisogno e alle esigenze di muoversi di tutti i bambini",
      "evidence_location": "Pagina 17"
    },
    {
      "titolo_attivita": "Grafico-pittorico",
      "categoria_principale": "Laboratorio",
      "descrizione_e_metodologia": "Manipolazione di materiali, disegno e pittura per stimolare l'immaginazione e la creatività.",
      "5w_chi": "Bambini",
      "5w_cosa": "Attività artistiche e creative.",
      "5w_dove": "Scuola",
      "5w_quando": "Non specificato",
      "5w_perche": "Sviluppare la creatività, le capacità espressive e comunicative.",
      "ore_dichiarate": "ND",
      "target": "Tutti i bambini",
      "evidence_quote": "stimolare l’immaginazione e la creatività",
      "evidence_location": "Pagina 18"
    },
    {
      "titolo_attivita": "Continuità Nido-Scuola dell’Infanzia",
      "categoria_principale": "Progetto",
      "descrizione_e_metodologia": "Incontri e attività condivise tra nido e scuola dell'infanzia per facilitare l'inserimento dei bambini.",
      "5w_chi": "Bambini, educatori, genitori",
      "5w_cosa": "Visite reciproche, attività congiunte, condivisione di informazioni.",
      "5w_dove": "Nido e Scuola dell'Infanzia",
      "5w_quando": "Non specificato",
      "5w_perche": "Facilitare l'inserimento dei bambini e garantire la continuità educativa.",
      "ore_dichiarate": "ND",
      "target": "Bambini che passano dal nido alla scuola dell'infanzia",
      "evidence_quote": "facilitare un inserimento più sereno e graduale nella nuova realtà scolastica",
      "evidence_location": "Pagina 19"
    }
  ],
  "narrative": "# Analisi del PTOF LEMM803035\n\n## Report di Valutazione dell'Orientamento\n\n### 1. Sintesi Generale\n\nIl presente report analizza la sezione dedicata all'orientamento all'interno del Piano Triennale dell'Offerta Formativa (PTOF) dell'Istituto Comprensivo **Falcone E Borsellino - Patu'** (LEMM803035) per il triennio 2019/2022. La scuola, di I grado, situata nel territorio non metropolitano di Patu' in provincia di Lecce e regione Puglia, è un istituto statale. L'analisi si basa sui dati forniti, valutando la presenza di una sezione dedicata all'orientamento, le partnership attivate, le finalità educative, gli obiettivi, le azioni messe in atto, l'offerta didattica orientativa e le attività opzionali. In generale, l'orientamento è affrontato in modo frammentario, con una mancanza di una sezione specifica dedicata e una scarsa esplicitazione di obiettivi e azioni mirate.\n\n### 2. Analisi Dimensionale\n\n**2.1 Orientamento - Sezione Dedicata:** Il PTOF non prevede una sezione specificamente dedicata all'orientamento, ottenendo un punteggio di 2. L'orientamento viene menzionato in modo implicito nella presentazione della scuola e nei progetti proposti, ma manca una trattazione organica e sistematica.\n\n**2.2 Partnership:** La scuola ha stabilito diverse partnership con enti e istituzioni del territorio, tra cui il **Consultorio Familiare**, l'**ASL**, **Cittadinanza Attiva**, l'**auditorium della Conciliazione**, il **teatro Ghione**, la **biblioteca comunale Valle Aurelia**, **enti culturali**, le **famiglie**, un **funzionario educativo (G.L.H.)** e **operatori della A.S.L.**, per un totale di 10 collaborazioni.\n\n**2.3 Finalità:** Le finalità educative del PTOF evidenziano l'impegno a promuovere lo sviluppo dell’**identità**, dell’**autonomia** e della **competenza** degli studenti (punteggio 3). Si sottolinea anche l'importanza di stimolare i bambini a conoscere e sentire le proprie esigenze (punteggio 3). Tuttavia, manca una chiara esplicitazione di finalità legate alla progettazione della vita e allo sviluppo di capacità orientative per affrontare le transizioni formative, sebbene venga menzionata la **Continuità Nido-Scuola dell’Infanzia** (punteggio 3).\n\n**2.4 Obiettivi:** Tra gli obiettivi del PTOF, la riduzione dell'**abbandono** scolastico ottiene un punteggio di 1, mentre la **continuità territoriale** raggiunge un punteggio di 4. Gli obiettivi di contrasto al fenomeno **NEET** e di promozione del **lifelong learning** ricevono un punteggio di 1 e 2 rispettivamente.\n\n**2.5 Azioni di Sistema:** Le azioni di sistema messe in atto dalla scuola mostrano un buon coordinamento dei servizi (punteggio 4) e un forte coinvolgimento delle famiglie (punteggio 5). L'azione relativa al dialogo tra docenti e studenti ottiene un punteggio di 2, mentre il monitoraggio delle azioni è valutato con 2. Un punto di forza è rappresentato dal sistema integrato di inclusione e gestione delle fragilità (punteggio 5).\n\n**2.6 Didattica Orientativa:** La didattica proposta si basa sull'esperienza degli studenti (punteggio 5) e sull'utilizzo di **laboratori** (punteggio 6). La flessibilità degli spazi e dei tempi didattici ottiene un punteggio di 3, mentre l'approccio interdisciplinare è valutato con 4.\n\n**2.7 Opzionali e Facoltative:** L'offerta di attività opzionali include opzioni **laboratoriali espressive** (punteggio 5) e **ludico-ricreative** (punteggio 4), mentre le opzioni culturali e di volontariato ricevono un punteggio di 1. Le attività sportive ottengono un punteggio di 3.\n\n### 3. Punti di Forza\n\nI punti di forza del PTOF risiedono nel forte legame con il territorio, testimoniato dalle numerose partnership attivate, e nell'attenzione all'inclusione e alla gestione delle fragilità. L'offerta didattica, basata sull'esperienza e sull'utilizzo di laboratori, rappresenta un elemento positivo. Il coinvolgimento delle famiglie è un altro aspetto degno di nota. Progetti come **Progetti con il territorio** e **Continuità Nido-Scuola dell’Infanzia** dimostrano un impegno verso la comunità e la transizione educativa.\n\n### 4. Aree di Debolezza\n\nL'area di debolezza principale è l'assenza di una sezione dedicata all'orientamento all'interno del PTOF. Questo comporta una mancanza di chiarezza sugli obiettivi, le azioni e le strategie da adottare per supportare gli studenti nel loro percorso di crescita e di orientamento. Anche la scarsa esplicitazione di finalità legate alla progettazione della vita e allo sviluppo di capacità orientative rappresenta un limite.\n\n### 5. Gap Analysis\n\nIl gap principale riguarda la necessità di strutturare un approccio più sistematico all'orientamento, definendo obiettivi specifici, azioni mirate e indicatori di valutazione. È necessario integrare l'orientamento in tutte le dimensioni del PTOF, coinvolgendo tutti gli attori coinvolti (docenti, studenti, famiglie, partner).\n\n### 6. Conclusioni\n\nIl PTOF dell'Istituto Comprensivo Falcone E Borsellino - Patu' presenta un quadro complessivo positivo, con un forte legame con il territorio e un'attenzione all'inclusione. Tuttavia, per migliorare l'efficacia dell'azione orientativa, è necessario colmare il gap esistente attraverso la definizione di una sezione dedicata, la chiara esplicitazione di obiettivi e azioni, e l'integrazione dell'orientamento in tutte le dimensioni del PTOF. Attività come l'**orto-giardino**, il **laboratorio sensoriale**, la **psicomotricità** e il **grafico-pittorico** rappresentano buone pratiche che, se integrate in un quadro orientativo più ampio, possono contribuire a sviluppare le competenze e le capacità degli studenti."
}