{
  "metadata": {
    "school_id": "MBMM8DN017",
    "denominazione": "Scuola Media \"E.Fermi\"",
    "tipo_scuola": "I Grado",
    "ordine_grado": "I Grado",
    "area_geografica": "Nord Ovest",
    "territorio": "Nord",
    "comune": "Villasanta",
    "anno_ptof": "2016-2019",
    "provincia": "Monza E Della Brianza",
    "regione": "Lombardia",
    "statale_paritaria": "Statale",
    "indirizzo": "Via A. Villa 5",
    "cap": "20852",
    "email": "mbic8dn006@istruzione.it",
    "pec": "ND",
    "website": "www.icvillasanta.edu.it",
    "tipo_scuola_dettaglio": "Scuola Primo Grado"
  },
  "ptof_section2": {
    "2_1_ptof_orientamento_sezione_dedicata": {
      "has_sezione_dedicata": 1,
      "score": 5,
      "note": "Esiste una sezione dedicata all'orientamento, sebbene integrata con altri temi come la sostenibilità. La trattazione è buona, con obiettivi e azioni definite, ma l'approccio integrato potrebbe diluire la specificità dell'orientamento."
    },
    "2_2_partnership": {
      "partner_nominati": [
        "Società e centri sportivi",
        "Case per anziani",
        "Biblioteca",
        "Avis",
        "Parrocchia",
        "Oratorio",
        "Gruppo Astrofili",
        "Circolo Amici dell’arte",
        "Corpo Musicale",
        "Alpini",
        "Pro Loco",
        "CRI",
        "Vigili",
        "Caritas",
        "Consulotorio di Monza",
        "Università Bocconi di Milano",
        "Scuole superiori",
        "Provincia",
        "Asso lombarda",
        "Associazioni Industriali",
        "Cooperativa La Speranza",
        "Associazione Genitori",
        "Comune",
        "Scuole dell'infanzia",
        "Scuole Primarie",
        "Scuole Secondarie di Primo Grado",
        "Enti Locali",
        "Nidi di Villasanta",
        "Scuola dell'Infanzia San Giorgio",
        "Associazione Scacchi2000",
        "Orchestra Felice",
        "Volontari",
        "Doposcuola comunale",
        "Oratoriano",
        "Associazione Mateinitaly",
        "Rete di Scopo",
        "Rete Trevi",
        "La Nostra Famiglia",
        "CTS/CTI MB",
        "British Council"
      ],
      "partnership_count": 32
    },
    "2_3_finalita": {
      "finalita_attitudini": {
        "score": 4,
        "evidence_quote": "accompagnando la persona ad esprimere in modo pieno tutte le sue potenzialità",
        "evidence_location": "Pagina 30"
      },
      "finalita_interessi": {
        "score": 4,
        "evidence_quote": "educando gli alunni all’ascolto, all’attenzione e alla riflessione",
        "evidence_location": "Pagina 30"
      },
      "finalita_progetto_vita": {
        "score": 5,
        "evidence_quote": "orienta gli allievi verso comportamenti positivi",
        "evidence_location": "Pagina 30"
      },
      "finalita_transizioni_formative": {
        "score": 5,
        "evidence_quote": "Continuità e orientamento sono menzionati come aree di intervento",
        "evidence_location": "Pagina 44"
      },
      "finalita_capacita_orientative_opportunita": {
        "score": 5,
        "evidence_quote": "promuovendo percorsi formativi individualizzati/personalizzati",
        "evidence_location": "Pagina 30"
      }
    },
    "2_4_obiettivi": {
      "obiettivo_ridurre_abbandono": {
        "score": 6
      },
      "obiettivo_continuita_territorio": {
        "score": 6
      },
      "obiettivo_contrastare_neet": {
        "score": 3
      },
      "obiettivo_lifelong_learning": {
        "score": 5
      }
    },
    "2_5_azioni_sistema": {
      "azione_coordinamento_servizi": {
        "score": 6
      },
      "azione_dialogo_docenti_studenti": {
        "score": 5
      },
      "azione_rapporto_scuola_genitori": {
        "score": 5
      },
      "azione_monitoraggio_azioni": {
        "score": 4
      },
      "azione_sistema_integrato_inclusione_fragilita": {
        "score": 6
      }
    },
    "2_6_didattica_orientativa": {
      "didattica_da_esperienza_studenti": {
        "score": 5
      },
      "didattica_laboratoriale": {
        "score": 4
      },
      "didattica_flessibilita_spazi_tempi": {
        "score": 4
      },
      "didattica_interdisciplinare": {
        "score": 5
      }
    },
    "2_7_opzionali_facoltative": {
      "opzionali_culturali": {
        "score": 5
      },
      "opzionali_laboratoriali_espressive": {
        "score": 5
      },
      "opzionali_ludiche_ricreative": {
        "score": 4
      },
      "opzionali_volontariato": {
        "score": 5
      },
      "opzionali_sportive": {
        "score": 5
      }
    }
  },
  "activities_register": [
    {
      "titolo_attivita": "Progetti d'istituto",
      "categoria_principale": "Progetto",
      "descrizione_e_metodologia": "Vari progetti che coinvolgono gli studenti in attività diverse",
      "5w_chi": "Tutti gli studenti",
      "5w_cosa": "Realizzazione di progetti didattici e extracurriculari",
      "5w_dove": "Scuola e territorio",
      "5w_quando": "Durante l'anno scolastico",
      "5w_perche": "Sviluppo di competenze e interessi",
      "ore_dichiarate": "ND",
      "target": "Tutti",
      "evidence_quote": "Progetti d'istituto",
      "evidence_location": "Pagina 121"
    },
    {
      "titolo_attivita": "Progetto Spazio allo Spazio",
      "categoria_principale": "Progetto",
      "descrizione_e_metodologia": "Progetto multidisciplinare che coinvolge diverse aree del sapere e promuove l'apertura verso il mondo esterno.",
      "5w_chi": "Alunni di tutti i gradi",
      "5w_cosa": "Attività didattiche, visite, incontri con esperti.",
      "5w_dove": "Scuola, luoghi esterni (musei, aziende, ecc.)",
      "5w_quando": "Durante l'anno scolastico",
      "5w_perche": "Sviluppo di competenze e interessi",
      "ore_dichiarate": "ND",
      "target": "Tutti gli alunni",
      "evidence_quote": "Progetto Spazio allo spazio",
      "evidence_location": "Pagina 35, 36, 46"
    },
    {
      "titolo_attivita": "Incontri con professionisti",
      "categoria_principale": "Incontro",
      "descrizione_e_metodologia": "Incontri con professionisti di diversi settori per far conoscere agli studenti le opportunità lavorative.",
      "5w_chi": "Alunni della scuola secondaria",
      "5w_cosa": "Presentazioni, testimonianze, domande e risposte.",
      "5w_dove": "Scuola",
      "5w_quando": "Durante l'anno scolastico",
      "5w_perche": "Orientare gli studenti nella scelta del percorso professionale.",
      "ore_dichiarate": "ND",
      "target": "Alunni della scuola secondaria",
      "evidence_quote": "SPAZIO ALLO SPAZIO",
      "evidence_location": "Pagina 46"
    },
    {
      "titolo_attivita": "Progetto IBI/BEI",
      "categoria_principale": "Progetto",
      "descrizione_e_metodologia": "Progetto di istruzione bilingue con approccio interdisciplinare e utilizzo della metodologia CLIL.",
      "5w_chi": "Alunni delle scuole primaria e secondaria",
      "5w_cosa": "Insegnamento di alcune discipline in lingua inglese.",
      "5w_dove": "Scuola",
      "5w_quando": "Annuale",
      "5w_perche": "Valorizzazione delle competenze linguistiche e sviluppo di competenze interculturali.",
      "ore_dichiarate": "6 ore settimanali (primaria)",
      "target": "Alunni primaria e secondaria",
      "evidence_quote": "valorizzazione e il sostegno all'apprendimento della lingua inglese",
      "evidence_location": "Pagina 111"
    },
    {
      "titolo_attivita": "Progetto Accoglienza",
      "categoria_principale": "Progetto",
      "descrizione_e_metodologia": "Incontri e attività per facilitare l'integrazione di nuovi alunni e genitori.",
      "5w_chi": "Nuovi alunni e genitori",
      "5w_cosa": "Presentazione della scuola, attività di conoscenza reciproca.",
      "5w_dove": "Scuola",
      "5w_quando": "Inizio anno scolastico",
      "5w_perche": "Favorire l'inserimento e la partecipazione attiva alla vita scolastica.",
      "ore_dichiarate": "ND",
      "target": "Nuovi alunni e genitori",
      "evidence_quote": "creare delle aspettative positive",
      "evidence_location": "Pagina 112"
    },
    {
      "titolo_attivita": "Progetto Intercultura",
      "categoria_principale": "Progetto",
      "descrizione_e_metodologia": "Attività per promuovere la convivenza multietnica e l'apprendimento della lingua e cultura italiana.",
      "5w_chi": "Tutti gli alunni",
      "5w_cosa": "Laboratori, attività didattiche, coinvolgimento delle famiglie e mediatori culturali.",
      "5w_dove": "Scuola",
      "5w_quando": "Annuale",
      "5w_perche": "Educare alla diversità e promuovere l'integrazione.",
      "ore_dichiarate": "ND",
      "target": "Tutti gli alunni",
      "evidence_quote": "educare e favorire la convivenza multietnica",
      "evidence_location": "Pagina 112"
    },
    {
      "titolo_attivita": "Spazio Allo Spazio",
      "categoria_principale": "Progetto",
      "descrizione_e_metodologia": "Progetto interdisciplinare per formazione uomo e cittadino, supporto inclusione disabili.",
      "5w_chi": "Alunni con disabilità",
      "5w_cosa": "Attività per inclusione e orientamento",
      "5w_dove": "Scuola",
      "5w_quando": "Non specificato",
      "5w_perche": "Formazione uomo e cittadino, inclusione",
      "ore_dichiarate": "ND",
      "target": "Alunni con disabilità",
      "evidence_quote": "Progetto pilota",
      "evidence_location": "Pagina 135"
    },
    {
      "titolo_attivita": "Progetto Teatro in Lingua Francese e Inglese",
      "categoria_principale": "Progetto",
      "descrizione_e_metodologia": "Migliorare capacità memorizzazione e drammatizzazione",
      "5w_chi": "Alunni",
      "5w_cosa": "Spettacoli in lingua",
      "5w_dove": "Scuola",
      "5w_quando": "Non specificato",
      "5w_perche": "Acquisizione lessico e pronuncia",
      "ore_dichiarate": "ND",
      "target": "Alunni",
      "evidence_quote": "Migliora le capacità di memorizzazione",
      "evidence_location": "Pagina 135"
    },
    {
      "titolo_attivita": "Progetto Minibasket",
      "categoria_principale": "Progetto",
      "descrizione_e_metodologia": "Avvicinare al minibasket con regole semplificate.",
      "5w_chi": "Classi terze",
      "5w_cosa": "Attività di minibasket",
      "5w_dove": "Scuola",
      "5w_quando": "Non specificato",
      "5w_perche": "Facilitare l'approccio allo sport",
      "ore_dichiarate": "ND",
      "target": "Classi terze",
      "evidence_quote": "Regole semplificate",
      "evidence_location": "Pagina 136"
    },
    {
      "titolo_attivita": "Progetto Pallavolo",
      "categoria_principale": "Progetto",
      "descrizione_e_metodologia": "Sviluppare motricità raffinata e collaborazione.",
      "5w_chi": "Classi IV-V",
      "5w_cosa": "Attività di pallavolo",
      "5w_dove": "Scuola",
      "5w_quando": "Non specificato",
      "5w_perche": "Sviluppo competenze motorie e collaborazione",
      "ore_dichiarate": "ND",
      "target": "Classi IV-V",
      "evidence_quote": "Sviluppare motricità raffinata",
      "evidence_location": "Pagina 136"
    },
    {
      "titolo_attivita": "IO HO SCELTO",
      "categoria_principale": "Progetto",
      "descrizione_e_metodologia": "chiede una libera adesione ed impegno alla lotta contro ogni forma di sopraffazione ed omertà, predispone elezioni interne alle classi, con nomina di un rappresentante, coordina attraverso un docente referente il gruppo degli alunni rappresentanti di tutte le classi, allo scopo di agire una gestione condivisa dei problemi di relazione interni alle classi.",
      "5w_chi": "Alunni, docenti, genitori",
      "5w_cosa": "Elezione di rappresentanti di classe, gestione dei problemi di relazione",
      "5w_dove": "Scuola",
      "5w_quando": "Annuale",
      "5w_perche": "Promuovere la cittadinanza attiva e la gestione dei conflitti",
      "ore_dichiarate": "ND",
      "target": "Tutte le classi",
      "evidence_quote": null,
      "evidence_location": "Pagina 135"
    },
    {
      "titolo_attivita": "Progetto di prevenzione bullismo ed educazione alla prosocialità",
      "categoria_principale": "Progetto",
      "descrizione_e_metodologia": "attuato in tutte le classi quarte e quinte della primaria e prime della secondaria, la scuola accompagna la riflessione su corrette regole di vita, con l'ausilio di volontari della CRI locale.",
      "5w_chi": "Alunni di classi quarte e quinte primaria e prime secondaria, volontari CRI",
      "5w_cosa": "Riflessione sulle regole di vita e prevenzione del bullismo",
      "5w_dove": "Scuola",
      "5w_quando": "Annuale",
      "5w_perche": "Promuovere la prosocialità e prevenire il bullismo",
      "ore_dichiarate": "ND",
      "target": "Classi quarte e quinte primaria e prime secondaria",
      "evidence_quote": null,
      "evidence_location": "Pagina 135"
    },
    {
      "titolo_attivita": "Progetto di educazione stradale",
      "categoria_principale": "Progetto",
      "descrizione_e_metodologia": "educa al rispetto delle regole e ad una mobilità sostenibile (pedibus), collaborando col corpo di polizia municipale.",
      "5w_chi": "Alunni, corpo di polizia municipale",
      "5w_cosa": "Educazione al rispetto delle regole stradali e alla mobilità sostenibile",
      "5w_dove": "Scuola, strade",
      "5w_quando": "Annuale",
      "5w_perche": "Promuovere la sicurezza stradale e la mobilità sostenibile",
      "ore_dichiarate": "ND",
      "target": "Tutte le classi",
      "evidence_quote": null,
      "evidence_location": "Pagina 136"
    },
    {
      "titolo_attivita": "Innovare la didattica della matematica",
      "categoria_principale": "Formazione",
      "descrizione_e_metodologia": "Approcci laboratoriali",
      "5w_chi": "Docenti",
      "5w_cosa": "Formazione su approcci laboratoriali in matematica",
      "5w_dove": "Online, aula",
      "5w_quando": "80 ore",
      "5w_perche": "Innovare la didattica",
      "ore_dichiarate": "80",
      "target": "Docenti",
      "evidence_quote": "innovare la didattica della matematica, con approcci laboratoriali",
      "evidence_location": "Pagina 186"
    },
    {
      "titolo_attivita": "Flipped Classroom",
      "categoria_principale": "Formazione",
      "descrizione_e_metodologia": "Formazione online",
      "5w_chi": "Docenti",
      "5w_cosa": "Formazione sulla metodologia Flipped Classroom",
      "5w_dove": "Online",
      "5w_quando": "3 ore",
      "5w_perche": "Innovare la metodologia didattica",
      "ore_dichiarate": "3",
      "target": "Docenti",
      "evidence_quote": "innovare la metodologia didattica",
      "evidence_location": "Pagina 186"
    },
    {
      "titolo_attivita": "Corso di Inglese A1",
      "categoria_principale": "Formazione",
      "descrizione_e_metodologia": "Corso, esame e certificazione",
      "5w_chi": "Docenti",
      "5w_cosa": "Acquisire competenze base di lingua inglese",
      "5w_dove": "British Council",
      "5w_quando": "30 ore",
      "5w_perche": "Seguire lavori di docenti della primaria",
      "ore_dichiarate": "30",
      "target": "Docenti",
      "evidence_quote": "acquisire competenze base di lingua inglese per seguire con consapevolezza i lavori di una doc. della primaria",
      "evidence_location": "Pagina 188"
    }
  ],
  "narrative": "# Analisi del PTOF MBMM8DN017\n\n## Report di Valutazione dell'Orientamento\n\n### 1. Sintesi Generale\n\nIl presente report analizza la sezione dedicata all'orientamento all'interno del Piano Triennale dell'Offerta Formativa (PTOF) della Scuola Media “E. Fermi” (MBMM8DN017) per il periodo 2016-2019. La scuola, situata nel territorio non metropolitano di Villasanta, in provincia di Monza e della Brianza, si distingue per un approccio all'orientamento che, pur integrato con tematiche più ampie come la sostenibilità, presenta una buona definizione di obiettivi e azioni. L'istituto dimostra una forte attenzione alla costruzione di **partnership** con un ampio ventaglio di soggetti, tra cui enti locali, associazioni, aziende e istituzioni universitarie. L'orientamento è concepito come un processo volto ad accompagnare gli studenti nello sviluppo delle loro potenzialità, interessi e nella costruzione del loro **progetto di vita**, con particolare attenzione alle **transizioni formative**.\n\n### 2. Analisi Dimensionale\n\n**2.1 Orientamento - Sezione Dedicata:** Il PTOF prevede una sezione dedicata all'orientamento, valutata con un punteggio di 5. Si evidenzia una trattazione complessivamente buona, ma l'integrazione con altri temi potrebbe diluire la specificità dell'azione orientativa.\n\n**2.2 Partnership:** La scuola vanta un elevato numero di **partnership** (32), che includono **società sportive**, **case per anziani**, **biblioteche**, **Avis**, **parrocchie**, **oratori**, **gruppi astrofili**, **circoli artistici**, **corpi musicali**, **alpini**, **pro loco**, **CRI**, **vigili**, **Caritas**, **consulotorio**, **Università Bocconi**, **scuole superiori**, **provincia**, **Asso lombarda**, **associazioni industriali**, **cooperative**, **associazioni genitori**, **comune**, **scuole dell'infanzia, primarie e secondarie di primo grado**, **enti locali**, **nidi**, **scuola dell'infanzia San Giorgio**, **Associazione Scacchi2000**, **Orchestra Felice**, **volontari**, **doposcuola comunale**, **oratoriano**, **Associazione Mateinitaly**, **Rete di Scopo**, **Rete Trevi**, **La Nostra Famiglia**, **CTS/CTI MB** e **British Council**.\n\n**2.3 Finalità:** Le finalità dell'orientamento sono ben definite. L'istituto mira ad accompagnare la persona ad esprimere le sue potenzialità (punteggio 4), educare all'ascolto e alla riflessione (punteggio 4), orientare verso comportamenti positivi (punteggio 5), garantire la continuità e l'orientamento (punteggio 5) e promuovere percorsi formativi individualizzati (punteggio 5).\n\n**2.4 Obiettivi:** Gli obiettivi del PTOF includono la riduzione dell'**abbandono scolastico** (punteggio 6), la continuità territoriale (punteggio 6), il contrasto alla condizione **NEET** (punteggio 3), il **lifelong learning** (punteggio 5).\n\n**2.5 Azioni di Sistema:** Le azioni di sistema previste sono il coordinamento dei servizi (punteggio 6), il dialogo tra docenti e studenti (punteggio 5), il rapporto scuola-genitori (punteggio 5), il monitoraggio delle azioni (punteggio 4) e la creazione di un sistema integrato per l'inclusione e la fragilità (punteggio 6).\n\n**2.6 Didattica Orientativa:** La didattica orientativa si basa sull'apprendimento dall'esperienza degli studenti (punteggio 5), sull'utilizzo di laboratori (punteggio 4), sulla flessibilità degli spazi e dei tempi (punteggio 4) e sull'approccio interdisciplinare (punteggio 5).\n\n**2.7 Opzionali e Facoltative:** L'offerta di attività opzionali e facoltative comprende opzionali culturali (punteggio 5), laboratoriali ed espressive (punteggio 5), ludiche e ricreative (punteggio 4), di **volontariato** (punteggio 5) e sportive (punteggio 5).\n\n### 3. Punti di Forza\n\nI punti di forza del PTOF risiedono nella vasta rete di **partnership** attivate, nella chiarezza delle finalità e degli obiettivi, nella coerenza delle azioni di sistema e nella varietà dell'offerta didattica e delle attività opzionali. Particolarmente apprezzabile è l'attenzione all'inclusione e alla valorizzazione delle competenze individuali degli studenti. Tra le attività registrate, si segnalano i **Progetti d'istituto**, il **Progetto Spazio allo Spazio**, gli **Incontri con professionisti**, il **Progetto IBI/BEI**, il **Progetto Accoglienza**, il **Progetto Intercultura**, il progetto **IO HO SCELTO** e i progetti di prevenzione del **bullismo** e di educazione stradale.\n\n### 4. Aree di Debolezza\n\nL'area di debolezza principale risiede nell'integrazione dell'orientamento con altre tematiche, che potrebbe diluirne la specificità. L'obiettivo di contrasto alla condizione **NEET** risulta meno prioritario rispetto agli altri. Inoltre, la documentazione relativa alle attività registrate spesso manca di informazioni dettagliate, come il numero di ore dedicate.\n\n### 5. Gap Analysis\n\nIl gap principale riguarda la necessità di rafforzare la specificità dell'azione orientativa, definendo interventi mirati e distinti dalle altre attività. È inoltre auspicabile un maggiore dettaglio nella documentazione delle attività, con l'indicazione del numero di ore dedicate e dei risultati ottenuti.\n\n### 6. Conclusioni\n\nIl PTOF della Scuola Media “E. Fermi” presenta un approccio all'orientamento solido e ben strutturato, supportato da una vasta rete di **partnership** e da un'offerta didattica diversificata. Pur con alcune aree di miglioramento, l'istituto dimostra un impegno significativo nel promuovere lo sviluppo delle competenze e degli interessi degli studenti, preparandoli ad affrontare le sfide del futuro e a costruire il proprio **progetto di vita**. L'implementazione di azioni mirate a rafforzare la specificità dell'orientamento e a migliorare la documentazione delle attività consentirebbe di ottimizzare ulteriormente l'efficacia del PTOF."
}