{
  "metadata": {
    "school_id": "PZEE88304R",
    "denominazione": "Giuliano-Ic Busciolano Pz",
    "tipo_scuola": "Primaria",
    "ordine_grado": "Primaria",
    "area_geografica": "Sud",
    "territorio": "Sud",
    "comune": "Potenza",
    "anno_ptof": "2022-2025",
    "provincia": "Potenza",
    "regione": "Basilicata",
    "statale_paritaria": "Statale",
    "indirizzo": "Contrada Giuliano",
    "cap": "85100",
    "email": "pzic88300g@istruzione.it",
    "pec": "pzic88300g@pec.istruzione.it",
    "website": "www.icbusciolano.it",
    "tipo_scuola_dettaglio": "Scuola Primaria"
  },
  "ptof_section2": {
    "2_1_ptof_orientamento_sezione_dedicata": {
      "has_sezione_dedicata": 1,
      "score": 2,
      "note": "Esiste una sezione dedicata all'orientamento, denominata 'Modelli organizzativi' (Pagina 145-175), che include attività specifiche come 'Coordinamento delle azioni di orientamento degli alunni della Scuola Secondaria di I grado classe III' (Pagina 136)."
    },
    "2_2_partnership": {
      "partner_nominati": [
        "Enti Locali",
        "Associazioni",
        "Scuole",
        "Musei",
        "Istituti pubblici e privati",
        "ASL",
        "GLIR/GIT/Scuole polo per l’inclusione territoriale",
        "privato sociale e volontariato",
        "Università degli Studi di Basilicata",
        "Liceo Gropius",
        "IIS Stigliani",
        "IIS Duni",
        "Liceo classico Orazio Flacco",
        "IC Bella",
        "IC Torraca",
        "AICS",
        "Conservatorio di Musica G. Da Venosa",
        "Associazione Ludolandia",
        "MiM- URS per la Basilicata",
        "Enti pubblici di formazione e ricerca",
        "Ufficio Scolastico Regionale",
        "Enti accreditati MiM",
        "Agenzie formative"
      ],
      "partnership_count": 22
    },
    "2_3_finalita": {
      "finalita_attitudini": {
        "score": 3,
        "evidence_quote": "valorizzare le proprie attitudini e potenzialità",
        "evidence_location": "Pagina 16"
      },
      "finalita_interessi": {
        "score": 3,
        "evidence_quote": "stimolando e favorendo la diffusione del sapere",
        "evidence_location": "Pagina 16"
      },
      "finalita_progetto_vita": {
        "score": 3,
        "evidence_quote": "esperienza duratura di crescita personale e culturale",
        "evidence_location": "Pagina 50"
      },
      "finalita_transizioni_formative": {
        "score": 4,
        "evidence_quote": "Coordinare i risultati formativi all’interno dei tre ordini di scuola",
        "evidence_location": "Pagina 17"
      },
      "finalita_capacita_orientative_opportunita": {
        "score": 3,
        "evidence_quote": "Promuovere maggiori incontri in verticale tra gli ordini di scuola",
        "evidence_location": "Pagina 17"
      }
    },
    "2_4_obiettivi": {
      "obiettivo_ridurre_abbandono": {
        "score": 4
      },
      "obiettivo_continuita_territorio": {
        "score": 5
      },
      "obiettivo_contrastare_neet": {
        "score": 4
      },
      "obiettivo_lifelong_learning": {
        "score": 3
      }
    },
    "2_5_azioni_sistema": {
      "azione_coordinamento_servizi": {
        "score": 3
      },
      "azione_dialogo_docenti_studenti": {
        "score": 4
      },
      "azione_rapporto_scuola_genitori": {
        "score": 5
      },
      "azione_monitoraggio_azioni": {
        "score": 2
      },
      "azione_sistema_integrato_inclusione_fragilita": {
        "score": 4
      }
    },
    "2_6_didattica_orientativa": {
      "didattica_da_esperienza_studenti": {
        "score": 4
      },
      "didattica_laboratoriale": {
        "score": 3
      },
      "didattica_flessibilita_spazi_tempi": {
        "score": 4
      },
      "didattica_interdisciplinare": {
        "score": 5
      }
    },
    "2_7_opzionali_facoltative": {
      "opzionali_culturali": {
        "score": 5
      },
      "opzionali_laboratoriali_espressive": {
        "score": 5
      },
      "opzionali_ludiche_ricreative": {
        "score": 3
      },
      "opzionali_volontariato": {
        "score": 4
      },
      "opzionali_sportive": {
        "score": 4
      }
    }
  },
  "activities_register": [
    {
      "titolo_attivita": "Attuazione del curricolo verticale",
      "categoria_principale": "Progetto",
      "descrizione_e_metodologia": "Attuazione del curricolo verticale centrato sulla didattica laboratoriale, sull'uso di tecnologie e di strumenti innovativi nella didattica, sulla realizzazione di compiti di realtà e sull'utilizzo di criteri e di strumenti di valutazione condivisi.",
      "5w_chi": "Tutti gli studenti",
      "5w_cosa": "Curricolo verticale, didattica laboratoriale, tecnologie, strumenti innovativi, compiti di realtà, valutazione condivisa.",
      "5w_dove": "Scuola",
      "5w_quando": "Triennio 2022-2025",
      "5w_perche": "Miglioramento degli esiti scolastici e sviluppo delle competenze.",
      "ore_dichiarate": "ND",
      "target": "Tutti gli ordini di scuola",
      "evidence_quote": "Curricolo verticale",
      "evidence_location": "Pagina 20"
    },
    {
      "titolo_attivita": "Potenziamento delle attività di formazione",
      "categoria_principale": "Formazione",
      "descrizione_e_metodologia": "Percorsi di formazione per docenti per avere una ricaduta positiva sugli esiti degli studenti.",
      "5w_chi": "Personale docente",
      "5w_cosa": "Formazione continua",
      "5w_dove": "Scuola/Esterno",
      "5w_quando": "Triennio 2022-2025",
      "5w_perche": "Migliorare la qualità dell'insegnamento e gli esiti degli studenti.",
      "ore_dichiarate": "ND",
      "target": "Docenti",
      "evidence_quote": "Formazione certificata",
      "evidence_location": "Pagina 20"
    },
    {
      "titolo_attivita": "APPrendiMENTI innovATTIVI",
      "categoria_principale": "Progetto",
      "descrizione_e_metodologia": "Realizzazione di ambienti dotati di soluzioni digitali innovative ed arredi moderni che favoriscano la flessibilità nella gestione degli spazi e la diversificazione dei percorsi didattici.",
      "5w_chi": "Studenti",
      "5w_cosa": "Rinnovamento ambienti scolastici con tecnologie avanzate.",
      "5w_dove": "Scuola",
      "5w_quando": "01/01/2023 - 31/12/2024",
      "5w_perche": "Favorire una didattica moderna e inclusiva.",
      "ore_dichiarate": "ND",
      "target": "Tutti gli studenti",
      "evidence_quote": "riscrivere la quotidianità scolastica integrandola con tecnologie avanzate",
      "evidence_location": "Pagina 41"
    },
    {
      "titolo_attivita": "Animatore digitale: formazione del personale interno",
      "categoria_principale": "Formazione",
      "descrizione_e_metodologia": "Percorsi di formazione per il personale docente per avere una ricaduta positiva sugli esiti degli studenti.",
      "5w_chi": "Personale docente",
      "5w_cosa": "Formazione continua",
      "5w_dove": "Scuola/Esterno",
      "5w_quando": "01/01/2023 - 31/08/2024",
      "5w_perche": "Migliorare la qualità dell'insegnamento e gli esiti degli studenti.",
      "ore_dichiarate": "ND",
      "target": "Docenti",
      "evidence_quote": "Formazione certificata",
      "evidence_location": "Pagina 42"
    },
    {
      "titolo_attivita": "Transizione digitale",
      "categoria_principale": "Formazione",
      "descrizione_e_metodologia": "Formazione del personale scolastico sull'utilizzo di strumenti digitali e metodologie innovative.",
      "5w_chi": "Personale scolastico",
      "5w_cosa": "Aggiornamento sulle nuove procedure amministrative e competenze digitali.",
      "5w_dove": "Scuola",
      "5w_quando": "25/03/2024 - 30/09/2025",
      "5w_perche": "Supportare le attività didattiche con strumenti digitali.",
      "ore_dichiarate": "ND",
      "target": "Docenti, DSGA, personale ATA",
      "evidence_quote": "utilizzo sistematico di strumenti quali il coding, il pensiero computazionale",
      "evidence_location": "Pagina 43"
    },
    {
      "titolo_attivita": "stem e multilinguismo",
      "categoria_principale": "Progetto",
      "descrizione_e_metodologia": "Integrazione dei curricula STEM e multilinguistici attraverso attività innovative.",
      "5w_chi": "Studenti",
      "5w_cosa": "Sviluppo di competenze STEM e linguistiche.",
      "5w_dove": "Scuola",
      "5w_quando": "01/02/2024 - 15/05/2025",
      "5w_perche": "Promuovere l'innovazione e la preparazione al mondo del lavoro.",
      "ore_dichiarate": "ND",
      "target": "Studenti",
      "evidence_quote": "promuovere l’incremento di corsi linguistici che possano influenzare fortemente il curriculum",
      "evidence_location": "Pagina 45"
    },
    {
      "titolo_attivita": "Contrasto alla dispersione scolastica",
      "categoria_principale": "Progetto",
      "descrizione_e_metodologia": "Attività di supporto e rinforzo per prevenire la dispersione scolastica.",
      "5w_chi": "Studenti a rischio",
      "5w_cosa": "Rafforzamento delle competenze e motivazione degli studenti.",
      "5w_dove": "Scuola",
      "5w_quando": "17/04/2024 - 15/09/2025",
      "5w_perche": "Prevenire l'esclusione sociale e promuovere il benessere collettivo.",
      "ore_dichiarate": "ND",
      "target": "Studenti",
      "evidence_quote": "valorizzare le competenze linguistiche, logico-matematiche e scientifiche",
      "evidence_location": "Pagina 47"
    },
    {
      "titolo_attivita": "Corso ad indirizzo musicale",
      "categoria_principale": "Percorso didattico",
      "descrizione_e_metodologia": "Offerta di studio di uno strumento musicale (chitarra, percussioni, pianoforte, violino).",
      "5w_chi": "Studenti della scuola secondaria di primo grado",
      "5w_cosa": "Studio di uno strumento musicale e partecipazione all'orchestra scolastica.",
      "5w_dove": "Scuola",
      "5w_quando": "Durante l'anno scolastico",
      "5w_perche": "Stimolare le capacità espressive e razionali, educare all'ascolto e alla concentrazione, offrire opportunità di socializzazione.",
      "ore_dichiarate": "ND",
      "target": "Studenti I grado",
      "evidence_quote": "chitarra, percussioni, pianoforte, violino",
      "evidence_location": "Pagina 50"
    },
    {
      "titolo_attivita": "Percorsi CLIL",
      "categoria_principale": "Progetto Didattico",
      "descrizione_e_metodologia": "Insegnamento di discipline curriculari (geografia) in lingua straniera, metodologia CLIL.",
      "5w_chi": "Studenti classe III Scuola Secondaria I grado",
      "5w_cosa": "Apprendimento contenuti disciplinari e competenze linguistiche.",
      "5w_dove": "Scuola",
      "5w_quando": "Non specificato",
      "5w_perche": "Migliorare competenze linguistiche e apprendimento attivo.",
      "ore_dichiarate": "ND",
      "target": "Studenti",
      "evidence_quote": null,
      "evidence_location": "Pagina 88"
    },
    {
      "titolo_attivita": "Percorsi di alfabetizzazione in lingua francese e potenziamento",
      "categoria_principale": "Corso Linguistico",
      "descrizione_e_metodologia": "Alfabetizzazione francese (classi V primaria) e preparazione certificazioni (inglese e francese).",
      "5w_chi": "Studenti classi V primaria e I, II, III scuola secondaria I grado",
      "5w_cosa": "Potenziamento competenze linguistiche e certificazioni internazionali.",
      "5w_dove": "Scuola",
      "5w_quando": "Non specificato",
      "5w_perche": "Ottenere certificazioni linguistiche riconosciute.",
      "ore_dichiarate": "ND",
      "target": "Studenti",
      "evidence_quote": null,
      "evidence_location": "Pagina 89"
    },
    {
      "titolo_attivita": "Percorsi per il potenziamento della lingua inglese e Certificazione linguistica per docenti",
      "categoria_principale": "Formazione Docenti",
      "descrizione_e_metodologia": "Certificazioni linguistiche internazionali di lingua inglese (Percorsi D.M. 65 Intervento B).",
      "5w_chi": "Docenti",
      "5w_cosa": "Sviluppare competenze linguistiche e implementare pratiche innovative.",
      "5w_dove": "Scuola",
      "5w_quando": "Non specificato",
      "5w_perche": "Migliorare qualità insegnamento e partecipazione a progetti europei.",
      "ore_dichiarate": "ND",
      "target": "Docenti",
      "evidence_quote": null,
      "evidence_location": "Pagina 91"
    },
    {
      "titolo_attivita": "Lingua inglese per piccoli alunni",
      "categoria_principale": "Attività Ludica",
      "descrizione_e_metodologia": "Introduzione alla lingua inglese in modo ludico e naturale.",
      "5w_chi": "Studenti classi prime Scuola Primaria",
      "5w_cosa": "Stimolare curiosità e familiarità con la lingua inglese.",
      "5w_dove": "Scuola",
      "5w_quando": "Non specificato",
      "5w_perche": "Familiarizzare i bambini con la lingua inglese.",
      "ore_dichiarate": "ND",
      "target": "Studenti",
      "evidence_quote": null,
      "evidence_location": "Pagina 92"
    },
    {
      "titolo_attivita": "Rete di Scopo Nazionale e Regionale Scuola in Ospedale",
      "categoria_principale": "Progetto",
      "descrizione_e_metodologia": "Offerta didattico-educativa per pazienti in età scolare.",
      "5w_chi": "Studenti ospedalizzati",
      "5w_cosa": "Insegnamento in orario intero.",
      "5w_dove": "Ospedale San Carlo di Potenza e ASL Matera",
      "5w_quando": "Continuativo",
      "5w_perche": "Garantire il diritto allo studio e il benessere psico-fisico.",
      "ore_dichiarate": "24",
      "target": "Studenti ospedalizzati",
      "evidence_quote": "Offerta didattico-educativa in orario intero",
      "evidence_location": "Pagina 146"
    },
    {
      "titolo_attivita": "Progetto 'Innovative Lab'",
      "categoria_principale": "Laboratorio",
      "descrizione_e_metodologia": "Realizzazione di laboratori per l'occupabilità.",
      "5w_chi": "Studenti e docenti",
      "5w_cosa": "Laboratori tematici.",
      "5w_dove": "Locali scolastici",
      "5w_quando": "Decennale",
      "5w_perche": "Sviluppo di competenze per il mondo del lavoro.",
      "ore_dichiarate": "ND",
      "target": "Studenti",
      "evidence_quote": "Realizzazione di laboratori",
      "evidence_location": "Pagina 157"
    },
    {
      "titolo_attivita": "Convenzione con AICS",
      "categoria_principale": "Sport",
      "descrizione_e_metodologia": "Promozione dell'attività sportiva e inclusione.",
      "5w_chi": "Studenti",
      "5w_cosa": "Attività sportive.",
      "5w_dove": "Scuola e strutture AICS",
      "5w_quando": "Annuale",
      "5w_perche": "Promuovere la salute e l'inclusione.",
      "ore_dichiarate": "ND",
      "target": "Studenti",
      "evidence_quote": "Promozione dell'attività sportiva",
      "evidence_location": "Pagina 156"
    },
    {
      "titolo_attivita": "Giochiamo con la musica",
      "categoria_principale": "Progetto",
      "descrizione_e_metodologia": "Percorso formativo dedicato agli alunni con bisogni educativi speciali",
      "5w_chi": "Alunni con BES",
      "5w_cosa": "Attività per favorire la socialità e il recupero delle competenze",
      "5w_dove": "Scuola",
      "5w_quando": "Non specificato",
      "5w_perche": "Favorire la socialità, stimolare il recupero delle competenze",
      "ore_dichiarate": "ND",
      "target": "Alunni BES",
      "evidence_quote": "Percorsi formativi dedicati agli alunni con bisogni educativi speciali",
      "evidence_location": "Pagina 126"
    },
    {
      "titolo_attivita": "Un abbraccio a quattro zampe",
      "categoria_principale": "Progetto",
      "descrizione_e_metodologia": "Percorso formativo dedicato agli alunni con bisogni educativi speciali",
      "5w_chi": "Alunni con BES",
      "5w_cosa": "Attività per favorire la socialità e il recupero delle competenze",
      "5w_dove": "Scuola",
      "5w_quando": "Non specificato",
      "5w_perche": "Favorire la socialità, stimolare il recupero delle competenze",
      "ore_dichiarate": "ND",
      "target": "Alunni BES",
      "evidence_quote": "Percorsi formativi dedicati agli alunni con bisogni educativi speciali",
      "evidence_location": "Pagina 126"
    },
    {
      "titolo_attivita": "Il giardino didattico dell'IC BUSCIOLANO",
      "categoria_principale": "Progetto",
      "descrizione_e_metodologia": "Percorso formativo dedicato agli alunni con bisogni educativi speciali",
      "5w_chi": "Alunni con BES",
      "5w_cosa": "Attività per favorire la socialità e il recupero delle competenze",
      "5w_dove": "Scuola",
      "5w_quando": "Non specificato",
      "5w_perche": "Favorire la socialità, stimolare il recupero delle competenze",
      "ore_dichiarate": "ND",
      "target": "Alunni BES",
      "evidence_quote": "Percorsi formativi dedicati agli alunni con bisogni educativi speciali",
      "evidence_location": "Pagina 126"
    },
    {
      "titolo_attivita": "Numeri in gioco per alunni speciali",
      "categoria_principale": "Progetto",
      "descrizione_e_metodologia": "Percorso formativo dedicato agli alunni con bisogni educativi speciali",
      "5w_chi": "Alunni con BES",
      "5w_cosa": "Attività per favorire la socialità e il recupero delle competenze",
      "5w_dove": "Scuola",
      "5w_quando": "Non specificato",
      "5w_perche": "Favorire la socialità, stimolare il recupero delle competenze",
      "ore_dichiarate": "ND",
      "target": "Alunni BES",
      "evidence_quote": "Percorsi formativi dedicati agli alunni con bisogni educativi speciali",
      "evidence_location": "Pagina 126"
    }
  ],
  "narrative": "Il Piano Triennale dell'Offerta Formativa (PTOF) dell'I.C. \"Busciolano\" (2022-2025) si configura come un progetto educativo integrato, fondato su tre pilastri strategici: l'inclusione, la digitalizzazione e il potenziamento dei legami con il territorio. L'istituto pone particolare attenzione all'inclusione di tutti gli alunni, con particolare riferimento a quelli con Bisogni Educativi Speciali (BES), attraverso una serie di progetti dedicati e percorsi personalizzati, come evidenziato nella sezione specifica (Pagina 125-144). Parallelamente, il PTOF promuove l'innovazione didattica attraverso l'integrazione delle tecnologie digitali, con iniziative come 'APPrendiMENTI innovATTIVI' e la formazione del personale docente sull'utilizzo di strumenti digitali. Un elemento distintivo del piano è la forte attenzione alla costruzione di una rete di partenariati con enti locali, università, associazioni e istituzioni, al fine di arricchire l'offerta formativa e favorire l'orientamento degli studenti. La scuola si impegna a contrastare la dispersione scolastica e a promuovere la transizione verso l'istruzione superiore e il mondo del lavoro, con particolare attenzione ai percorsi NEET. Infine, il PTOF valorizza l'importanza delle attività extracurriculari, come i corsi musicali e le attività sportive, per lo sviluppo integrale della persona."
}